coco_toolkit/__init__.py
coco_toolkit/convertors/converter.py
coco_toolkit/helper/merge.py
coco_toolkit/helper/preprocess.py
coco_toolkit/helper/report.py
coco_toolkit/modules/cocoviewer.py
coco_toolkit/modules/voc2coco.py
coco_toolkit-0.1.0.dist-info/WHEEL
coco_toolkit-0.1.0.dist-info/METADATA
coco_toolkit-0.1.0.dist-info/RECORD
