Metadata-Version: 2.1
Name: coco-toolkit
Version: 0.1.0
Summary: A Reporer Everyting for traninig CocoDataset
Author: mcvarer
Author-email: murat@visiosoft.com.tr
Requires-Python: >=3.8,<4.0
Classifier: Programming Language :: Python :: 3
Classifier: Programming Language :: Python :: 3.10
Classifier: Programming Language :: Python :: 3.8
Classifier: Programming Language :: Python :: 3.9
Requires-Dist: addict (>=2.4.0,<3.0.0)
Requires-Dist: matplotlib (>=3.5.2,<4.0.0)
Requires-Dist: pre-commit (>=2.19.0,<3.0.0)
Requires-Dist: tqdm (>=4.64.0,<5.0.0)
